Products.TinyMCE-1.3.29-py2.7-nspkg.pth
Products/TinyMCE/__init__.py
Products/TinyMCE/bbb.py
Products/TinyMCE/configure.zcml
Products/TinyMCE/exportimport.py
Products/TinyMCE/profiles.zcml
Products/TinyMCE/setuphandlers.py
Products/TinyMCE/shortcut.py
Products/TinyMCE/upgrades.py
Products/TinyMCE/utility.py
Products/TinyMCE/vocabularies.py
Products/TinyMCE/Extensions/Install.py
Products/TinyMCE/adapters/JSONDetails.py
Products/TinyMCE/adapters/JSONFolderListing.py
Products/TinyMCE/adapters/JSONSearch.py
Products/TinyMCE/adapters/Save.py
Products/TinyMCE/adapters/Upload.py
Products/TinyMCE/adapters/__init__.py
Products/TinyMCE/adapters/caching.py
Products/TinyMCE/adapters/configure.zcml
Products/TinyMCE/adapters/interfaces/JSONDetails.py
Products/TinyMCE/adapters/interfaces/JSONFolderListing.py
Products/TinyMCE/adapters/interfaces/JSONSearch.py
Products/TinyMCE/adapters/interfaces/Save.py
Products/TinyMCE/adapters/interfaces/Upload.py
Products/TinyMCE/adapters/interfaces/__init__.py
Products/TinyMCE/browser/__init__.py
Products/TinyMCE/browser/atanchors.py
Products/TinyMCE/browser/browser.py
Products/TinyMCE/browser/compressor.py
Products/TinyMCE/browser/configure.zcml
Products/TinyMCE/browser/controlpanel.py
Products/TinyMCE/browser/dxanchors.py
Products/TinyMCE/browser/style.py
Products/TinyMCE/browser/tiny_mce_gzip.js
Products/TinyMCE/browser/url.py
Products/TinyMCE/browser/images/tinymce_icon.gif
Products/TinyMCE/browser/interfaces/__init__.py
Products/TinyMCE/browser/interfaces/anchors.py
Products/TinyMCE/browser/interfaces/browser.py
Products/TinyMCE/browser/interfaces/controlpanel.py
Products/TinyMCE/browser/interfaces/style.py
Products/TinyMCE/browser/interfaces/url.py
Products/TinyMCE/browser/stylesheets/tinymce.css
Products/TinyMCE/interfaces/__init__.py
Products/TinyMCE/interfaces/shortcut.py
Products/TinyMCE/interfaces/utility.py
Products/TinyMCE/locales/plone.tinymce-manual.pot
Products.TinyMCE-1.3.29.dist-info/METADATA
Products.TinyMCE-1.3.29.dist-info/RECORD
Products.TinyMCE-1.3.29.dist-info/WHEEL
Products.TinyMCE-1.3.29.dist-info/namespace_packages.txt
Products.TinyMCE-1.3.29.dist-info/top_level.txt
