Metadata-Version: 2.1
Name: Products.TinyMCE
Version: 1.3.29
Summary: Adds support for TinyMCE, a platform independent web based Javascript HTML WYSIWYG editor, to Plone.
Home-page: http://plone.org/products/tinymce
Author: Four Digits
Author-email: rob@fourdigits.nl
License: LGPL
Keywords: editor editors tinymce wysiwyg
Platform: UNKNOWN
Classifier: Framework :: Plone
Classifier: Framework :: Plone :: 4.3
Classifier: License :: OSI Approved :: GNU Library or Lesser General Public License (LGPL)
Classifier: Programming Language :: Python
Classifier: Programming Language :: Python :: 2.6
Classifier: Programming Language :: Python :: 2.7
Provides-Extra: test
Provides-Extra: docs
Requires-Dist: setuptools
Requires-Dist: plone.app.imaging (>=1.0.2)
Requires-Dist: plone.outputfilters
Requires-Dist: plone.namedfile
Requires-Dist: plone.app.layout (>=2.3.7)
Requires-Dist: plone.caching
Requires-Dist: Products.ResourceRegistries
Requires-Dist: zope.app.content
Requires-Dist: zope.schema (>=3.5.4)
Provides-Extra: docs
Requires-Dist: sphinx; extra == 'docs'
Provides-Extra: test
Requires-Dist: plone.app.testing; extra == 'test'
Requires-Dist: zope.testing; extra == 'test'
Requires-Dist: unittest2; extra == 'test'
Requires-Dist: Pillow; extra == 'test'
Requires-Dist: plone.app.dexterity; extra == 'test'
